CHANGES.rst
LICENSE.txt
MANIFEST.in
README.rst
setup.py
js/__init__.py
js.angular_xeditable.egg-info/PKG-INFO
js.angular_xeditable.egg-info/SOURCES.txt
js.angular_xeditable.egg-info/dependency_links.txt
js.angular_xeditable.egg-info/entry_points.txt
js.angular_xeditable.egg-info/namespace_packages.txt
js.angular_xeditable.egg-info/not-zip-safe
js.angular_xeditable.egg-info/requires.txt
js.angular_xeditable.egg-info/top_level.txt
js/angular_xeditable/__init__.py
js/angular_xeditable/test_angular-xeditable.txt
js/angular_xeditable/resources/css/xeditable.css
js/angular_xeditable/resources/css/xeditable.min.css
js/angular_xeditable/resources/js/xeditable.js
js/angular_xeditable/resources/js/xeditable.min.js