Metadata-Version: 1.0
Name: js.angular-xeditable
Version: 0.6.0.post1
Summary: Fanstatic packaging of Angular-xeditable
Home-page: UNKNOWN
Author: Fanstatic Developers
Author-email: fanstatic@googlegroups.com
License: BSD
Platform: UNKNOWN
